tri/__init__.py
tri/tables/__init__.py
tri/tables/templates/tri_tables/compact_form_row.html
tri/tables/templates/tri_tables/links.html
tri/tables/templates/tri_tables/list.html
tri/tables/templates/tri_tables/paginator.html
tri/tables/templates/tri_tables/table.html
tri/tables/templates/tri_tables/table_cell.html
tri/tables/templates/tri_tables/table_header_rows.html
tri/tables/templates/tri_tables/table_row.html
tri/tables/templatetags/__init__.py
tri/tables/templatetags/tri_tables.py
tri.tables-0.12.0.dist-info/DESCRIPTION.rst
tri.tables-0.12.0.dist-info/METADATA
tri.tables-0.12.0.dist-info/metadata.json
tri.tables-0.12.0.dist-info/RECORD
tri.tables-0.12.0.dist-info/top_level.txt
tri.tables-0.12.0.dist-info/WHEEL
