Metadata-Version: 2.0
Name: tri.tables
Version: 0.12.0
Summary: tri.tables is a library to make full featured HTML tables easily
Home-page: UNKNOWN
Author: Anders Hovmöller
Author-email: anders.hovmoller@trioptima.com
License: BSD
Keywords: tri.tables
Platform: UNKNOWN
Classifier: Development Status :: 2 - Pre-Alpha
Classifier: Intended Audience :: Developers
Classifier: License :: OSI Approved :: BSD License
Classifier: Natural Language :: English
Classifier: Programming Language :: Python :: 2
Classifier: Programming Language :: Python :: 2.6
Classifier: Programming Language :: Python :: 2.7
Classifier: Programming Language :: Python :: 3
Classifier: Programming Language :: Python :: 3.3
Requires-Dist: django
Requires-Dist: tri.declarative
Requires-Dist: tri.struct
